currconver/__init__.py
currconver/__main__.py
currconver-1.0.4.dist-info/METADATA
currconver-1.0.4.dist-info/WHEEL
currconver-1.0.4.dist-info/licenses/LICENSE
currconver-1.0.4.dist-info/RECORD
